LICENSE
README.md
setup.py
Dorker.egg-info/PKG-INFO
Dorker.egg-info/SOURCES.txt
Dorker.egg-info/dependency_links.txt
Dorker.egg-info/entry_points.txt
Dorker.egg-info/requires.txt
Dorker.egg-info/top_level.txt
dorker/__init__.py
dorker/dorker.py