Metadata-Version: 2.1
Name: Dorker
Version: 1.0.0
Summary: An advanced level CLI and API based Gogle dorking tool
Author: D.Sanjai Kumar
Author-email: bughunterz0047@gmail.com
License-File: LICENSE
